account_opening_analysis/__init__.py
account_opening_analysis/main.py
account_opening_analysis/tests.py
automatedIAReviewMicroservice-0.0.1.dist-info/METADATA
automatedIAReviewMicroservice-0.0.1.dist-info/WHEEL
automatedIAReviewMicroservice-0.0.1.dist-info/top_level.txt
automatedIAReviewMicroservice-0.0.1.dist-info/RECORD
