Metadata-Version: 2.1
Name: automatedIAReviewMicroservice
Version: 0.0.1
Summary: Automated Intenal Audit Review Package
Home-page: UNKNOWN
Author: Stephen Sanwo
Author-email: stephen.sanwo@icloud.com
License: UNKNOWN
Keywords: python,internal audit,risk,compliance
Platform: UNKNOWN
Classifier: Development Status :: 3 - Alpha
Classifier: Intended Audience :: Education
Classifier: Programming Language :: Python :: 3
Classifier: Operating System :: MacOS :: MacOS X
Classifier: Operating System :: Microsoft :: Windows
